<?xml version="1.0" encoding="UTF-8"?>
<programs majorVersion="2" minorVersion="0" revision="2" updated="2013-06-19T23:06:20" xmlns:xsi="http://www.w3.org/2001/XMLSchema-instance" xsi:noNamespaceSchemaLocation="GameSaveInfo202.xsd">
  <!--This file contains games, mods and expansions that start with the letter A
DO NOT EDIT THIS FILE, CHANGES WILL EVENTUALLY BE OVERWRITTEN BY THE AUTO UPDATE SYSTEM!-->
  <game name="AaaaaAAaaaAAAaaAAAAaAAAAA" added="1955-11-05T00:00:00" updated="1955-11-05T00:00:00">
    <title>AaaaaAAaaaAAAaaAAAAaAAAAA!!!</title>
    <version os="Windows">
      <locations>
        <path ev="localappdata" path="AaaaaRecklessDisregard"/>
      </locations>
      <files>
        <include/>
      </files>
      <linkable/>
      <contributor>duncans_pumpkin</contributor>
    </version>
  </game>
  <game name="Academagia" added="2013-06-14T05:17:42" updated="2013-06-14T05:17:42">
    <title>Academagia</title>
    <version os="Windows">
      <locations>
        <path ev="appdata" path="Academagia"/>
      </locations>
      <files>
        <include/>
      </files>
      <linkable/>
      <contributor>GameSaveManager</contributor>
    </version>
  </game>
  <game name="AceCombatAssaultHorizon" added="2013-02-23T21:39:00" updated="2013-02-23T21:39:00">
    <title>Ace Combat: Assault Horizon</title>
    <version os="Windows">
      <locations>
        <path ev="userdocuments" path="NAMCO\ACAH"/>
      </locations>
      <files>
        <include/>
      </files>
      <linkable/>
      <contributor>GameSaveManager</contributor>
    </version>
  </game>
  <game name="AcesOfTheGalaxy" added="1955-11-05T00:00:00" updated="1955-11-05T00:00:00">
    <title>Aces of the Galaxy</title>
    <version os="Windows">
      <locations>
        <path ev="userdocuments" path="My Games\Aces of the Galaxy"/>
      </locations>
      <files>
        <include/>
      </files>
      <linkable/>
      <contributor>GameSaveManager</contributor>
    </version>
  </game>
  <game name="Achron" added="1955-11-05T00:00:00" updated="1955-11-05T00:00:00">
    <title>Achron</title>
    <version os="Windows">
      <locations>
        <path ev="userdocuments" path="Achron"/>
      </locations>
      <files>
        <include/>
      </files>
      <linkable/>
      <contributor>GameSaveManager</contributor>
    </version>
  </game>
  <game name="AchtungPanzerOperationStar" added="2013-02-03T05:40:17" updated="2013-02-03T05:40:17">
    <title>Achtung Panzer: Operation Star</title>
    <version os="Windows">
      <locations>
        <registry root="local_machine" key="SOFTWARE\Microsoft\Windows\CurrentVersion\Uninstall\{688A396E-0C6B-4CC7-9B58-76619E9E530F}_is1" value="InstallLocation"/>
      </locations>
      <files>
        <include path="users\profiles"/>
      </files>
      <contributor>GameSaveManager</contributor>
    </version>
  </game>
  <game name="ActOfWarDirectAction" added="1955-11-05T00:00:00" updated="1955-11-05T00:00:00">
    <title>Act of War: Direct Action</title>
    <version os="Windows">
      <locations>
        <registry root="current_user" key="SOFTWARE\Eugen Systems\ActOfWar" value="AppDir"/>
      </locations>
      <files>
        <include path="AOW\Save"/>
      </files>
      <linkable path="AOW\Save"/>
      <contributor>GameSaveManager</contributor>
    </version>
  </game>
  <game name="ActOfWarHighTreason" added="1955-11-05T00:00:00" updated="1955-11-05T00:00:00">
    <title>Act of War: High Treason</title>
    <version os="Windows">
      <locations>
        <registry root="current_user" key="SOFTWARE\Eugen Systems\ActOfWar_HighTreason" value="AppDir"/>
      </locations>
      <files>
        <include path="AOW\Save"/>
      </files>
      <linkable path="AOW\Save"/>
      <contributor>GameSaveManager</contributor>
    </version>
  </game>
  <game name="AdamsVenture2" added="2013-02-03T05:40:17" updated="2013-02-03T05:40:17">
    <title>Adam's Venture 2</title>
    <version os="Windows">
      <locations>
        <path ev="userdocuments" path="My Games\VentureGame"/>
      </locations>
      <files>
        <include/>
      </files>
      <linkable/>
      <contributor>GameSaveManager</contributor>
    </version>
  </game>
  <game name="AdventRising" added="1955-11-05T00:00:00" updated="1955-11-05T00:00:00">
    <title>Advent Rising</title>
    <version os="Windows">
      <locations>
        <path ev="installlocation" path="GOG.com\Advent Rising"/>
        <path ev="steamcommon" path="advent rising"/>
        <registry root="local_machine" key="SOFTWARE\GOG.com\GOGADVENTRISING" value="PATH"/>
        <registry root="local_machine" key="SOFTWARE\Microsoft\Windows\CurrentVersion\Uninstall\Advent" value="UninstallString"/>
        <shortcut ev="startmenu" path="Programs\GOG.com\Advent Rising\Advent Rising.lnk" detract="System"/>
      </locations>
      <files>
        <include path="System\Saves"/>
      </files>
      <files type="Settings">
        <include path="System" filename="My*.ini"/>
      </files>
      <linkable path="System\Saves"/>
      <contributor>GameSave.Info</contributor>
    </version>
  </game>
  <game name="AdventuresofShuggy" added="2012-10-01T16:54:44" updated="2012-10-01T16:54:44">
    <title>Adventures of Shuggy</title>
    <version platform="SteamCloud">
      <locations>
        <path ev="steamuserdata" path="211440"/>
      </locations>
      <files>
        <include/>
      </files>
      <contributor>Arc Angel</contributor>
    </version>
  </game>
  <game name="AdventuresOfTintin" added="1955-11-05T00:00:00" updated="1955-11-05T00:00:00">
    <title>The Adventures of Tintin: The Game</title>
    <version os="Windows">
      <locations>
        <path ev="userdocuments" path="The Adventures of Tintin"/>
      </locations>
      <files>
        <include/>
      </files>
      <linkable/>
      <contributor>GameSaveManager</contributor>
    </version>
  </game>
  <game name="aeroflyFS" added="1955-11-05T00:00:00" updated="1955-11-05T00:00:00">
    <title>aeroflyFS</title>
    <version os="Windows">
      <locations>
        <path ev="userdocuments" path="aerofly FS"/>
      </locations>
      <files>
        <include/>
      </files>
      <linkable/>
      <contributor>GameSaveManager</contributor>
    </version>
  </game>
  <game name="AffairBureau" added="2013-02-03T05:40:17" updated="2013-02-03T05:40:17">
    <title>Affair Bureau</title>
    <version os="Windows">
      <locations>
        <path ev="appdata" path="Azuzaz Games\Bureau"/>
      </locations>
      <files>
        <include/>
      </files>
      <linkable/>
      <contributor>GameSaveManager</contributor>
    </version>
  </game>
  <game name="AfterfallInsanity" added="1955-11-05T00:00:00" updated="1955-11-05T00:00:00">
    <title>Afterfall: Insanity</title>
    <version os="Windows">
      <locations>
        <path ev="userdocuments" path="My Games\Afterfall InSanity"/>
      </locations>
      <files>
        <include path="Binaries\SaveData"/>
        <include path="RascalGame\SaveData"/>
      </files>
      <files type="Settings">
        <include path="RascalGame\Config"/>
      </files>
      <linkable/>
      <contributor>Arc Angel</contributor>
    </version>
  </game>
  <game name="AGameOfDwarves" added="2013-02-03T05:40:17" updated="2013-02-03T05:40:17">
    <title>A Game of Dwarves</title>
    <version os="Windows">
      <locations>
        <path ev="appdata" path="Zeal Game Studio\A Game of Dwarves"/>
      </locations>
      <files>
        <include/>
      </files>
      <linkable/>
      <contributor>GameSaveManager</contributor>
    </version>
  </game>
  <game name="AgathaChristieDeathOnTheNile" added="1955-11-05T00:00:00" updated="1955-11-05T00:00:00">
    <title>Agatha Christie: Death on the Nile</title>
    <version os="Windows">
      <locations>
        <path ev="appdata" path="FloodLightGames\Death on the Nile"/>
      </locations>
      <files>
        <include/>
      </files>
      <linkable/>
      <contributor>GameSaveManager</contributor>
    </version>
  </game>
  <game name="AgeOfConan" added="1955-11-05T00:00:00" updated="1955-11-05T00:00:00">
    <title>Age of Conan</title>
    <version os="Windows">
      <locations>
        <path ev="localappdata" path="Funcom\Conan"/>
      </locations>
      <files>
        <include/>
      </files>
      <linkable/>
      <contributor>GameSaveManager</contributor>
    </version>
  </game>
  <game name="AgeOfEmpires" added="2012-09-12T14:11:29" updated="2012-09-12T14:11:29">
    <title>Age of Empires</title>
    <version os="Windows">
      <locations>
        <registry root="local_machine" key="SOFTWARE\Microsoft\DirectPlay\Applications\Age of Empires" value="Path"/>
        <registry root="local_machine" key="SOFTWARE\Microsoft\Games\Age of Empires\1.00" value="InstallationDirectory"/>
      </locations>
      <files>
        <include filename="empires.GID"/>
        <include filename="game2.nfo"/>
        <include path="savegame"/>
      </files>
      <linkable path="savegame"/>
      <contributor>GameSaveManager</contributor>
    </version>
  </game>
  <game name="AgeOfEmpires2" added="1955-11-05T00:00:00" updated="2013-06-14T05:17:42">
    <title>Age of Empires II</title>
    <version os="Windows">
      <locations>
        <path ev="installlocation" path="Microsoft Games\Age of Empires II"/>
        <registry root="local_machine" key="SOFTWARE\Microsoft\DirectPlay\Applications\Age of Empires II" value="Path"/>
        <registry root="local_machine" key="SOFTWARE\Microsoft\Microsoft Games\Age of Empires\2.0" value="InstallationDirectory"/>
        <shortcut ev="startmenu" path="Programs\Microsoft Games\Age of Empires II\Age of Empires II.lnk"/>
      </locations>
      <files>
        <include filename="player.nfp"/>
        <include path="SaveGame"/>
        <include path="Scenario" filename="*.scx"/>
      </files>
      <linkable path="SaveGame"/>
      <contributor>Samuel Barbour</contributor>
    </version>
    <version os="Windows" release="HD">
      <title>Age of Empires II HD</title>
      <locations>
        <path ev="steamcommon" path="Age2HD"/>
      </locations>
      <files>
        <include path="SaveGame" filename="*.gax"/>
      </files>
      <files type="Scenarios">
        <include path="Scenario" filename="*.scx"/>
      </files>
      <files type="Settings">
        <include filename="player.nfp"/>
      </files>
      <linkable path="SaveGame"/>
      <contributor>GameSaveManager</contributor>
    </version>
  </game>
  <game name="AgeOfEmpires3" follows="AgeOfEmpires2" added="1955-11-05T00:00:00" updated="1955-11-05T00:00:00">
    <title>Age of Empires III</title>
    <version os="Windows">
      <locations>
        <path ev="userdocuments" path="My Games\Age of Empires 3"/>
      </locations>
      <files>
        <include path="Savegame"/>
        <include path="Users"/>
      </files>
      <linkable/>
      <contributor>SamuelTaylor</contributor>
    </version>
  </game>
  <game name="AgeOfMythology" added="1955-11-05T00:00:00" updated="1955-11-05T00:00:00">
    <title>Age of Mythology</title>
    <version os="Windows">
      <locations>
        <path ev="installlocation" path="Microsoft Games\Age of Mythology"/>
        <registry root="local_machine" key="SOFTWARE\Microsoft\Microsoft Games\Age of Mythology\1.0" value="AppPath"/>
        <shortcut ev="startmenu" path="Programs\Microsoft Games\Age of Mythology\Age of Mythology.lnk"/>
      </locations>
      <files>
        <include path="savegame" filename="*.rec"/>
        <include path="savegame" filename="*.sav"/>
      </files>
      <linkable path="savegame"/>
      <contributor>GameSave.Info</contributor>
    </version>
  </game>
  <expansion name="AgeOfMythologyTheTitansExpansion" for="AgeOfMythology" added="1955-11-05T00:00:00" updated="1955-11-05T00:00:00">
    <title>Age of Mythology: The Titans Expansion</title>
    <version os="Windows">
      <locations>
        <path ev="userdocuments" path="My Games\Age of Mythology"/>
      </locations>
      <files>
        <include path="Savegame" filename="*.rcx"/>
        <include path="Savegame" filename="*.svx"/>
      </files>
      <linkable/>
      <contributor>GameSave.Info</contributor>
    </version>
  </expansion>
  <game name="AgeOfOraclesTarasJourney" added="2013-02-03T05:40:17" updated="2013-02-03T05:40:17">
    <title>Age of Oracles: Tara's Journey</title>
    <version os="Windows">
      <locations>
        <path ev="localappdata" path="JollyBear\Age of Oracles Taras Journey"/>
      </locations>
      <files>
        <include/>
      </files>
      <linkable/>
      <contributor>GameSaveManager</contributor>
    </version>
  </game>
  <game name="AgeOfPirates2" added="1955-11-05T00:00:00" updated="1955-11-05T00:00:00">
    <title>Age of Pirates 2: City of Abandoned Ships</title>
    <version os="Windows">
      <locations>
        <registry root="local_machine" key="SOFTWARE\Playlogic\AoP2" value="InstallPath"/>
      </locations>
      <files>
        <include path="SAVE"/>
      </files>
      <linkable path="SAVE"/>
      <contributor>GameSaveManager</contributor>
    </version>
  </game>
  <game name="AgeOfWonders" added="1955-11-05T00:00:00" updated="1955-11-05T00:00:00">
    <title>Age of Wonders</title>
    <version os="Windows">
      <locations>
        <path ev="installlocation" path="GOG.com\Age of Wonders"/>
        <path ev="installlocation" path="Triumph Studios\Age of Wonders"/>
        <registry root="current_user" key="Software\Triumph Studios\Age of Wonders\General" value="Root Directory"/>
        <registry root="local_machine" key="SOFTWARE\GOG.com\GOGAOM1" value="PATH"/>
        <shortcut ev="startmenu" path="Programs\Age of Wonders\Age of Wonders.lnk"/>
        <shortcut ev="startmenu" path="Programs\GOG.com\Age of Wonders\Age of Wonders.lnk"/>
      </locations>
      <files>
        <include path="Save"/>
      </files>
      <linkable path="Save"/>
      <contributor>GameSave.Info</contributor>
    </version>
  </game>
  <game name="AgeOfWonders2" added="2012-10-01T16:54:44" updated="2013-02-03T05:40:17">
    <title>Age of Wonders II</title>
    <version os="Windows">
      <locations>
        <path ev="installlocation" path="GOG.com\Age of Wonders II"/>
        <registry root="current_user" key="Software\Triumph Studios\Age of Wonders II\General" value="Root Directory"/>
        <registry root="local_machine" key="SOFTWARE\GOG.com\GOGAOM2" value="PATH"/>
        <shortcut ev="startmenu" path="Programs\GOG.com\Age of Wonders 2\Age of Wonders 2.lnk"/>
      </locations>
      <files>
        <include path="Save"/>
      </files>
      <contributor>GameSave.Info</contributor>
      <contributor>GameSaveManager</contributor>
    </version>
  </game>
  <game name="AgeOfWondersShadowMagic" added="1955-11-05T00:00:00" updated="2013-02-03T05:40:17">
    <title>Age of Wonders: Shadow Magic</title>
    <version os="Windows">
      <locations>
        <path ev="installlocation" path="GOG.com\Age of Wonders Shadow Magic"/>
        <registry root="local_machine" key="SOFTWARE\GOG.com\GOGAOMSM" value="PATH"/>
        <shortcut ev="startmenu" path="Programs\GOG.com\Age of Wonders - Shadow Magic\Age of Wonders - Shadow Magic.lnk"/>
      </locations>
      <files>
        <include path="Save"/>
      </files>
      <linkable path="Save"/>
      <contributor>GameSave.Info</contributor>
    </version>
  </game>
  <game name="AgriculturalSimulator2011" added="2013-02-03T05:40:17" updated="2013-02-03T05:40:17">
    <title>Agricultural Simulator 2011</title>
    <version os="Windows">
      <locations>
        <path ev="userdocuments" path="My Games\agrar simulator 2011"/>
      </locations>
      <files>
        <include/>
      </files>
      <linkable/>
      <contributor>GameSaveManager</contributor>
    </version>
  </game>
  <game name="AIMRacing" added="1955-11-05T00:00:00" updated="2013-01-05T16:19:39">
    <title>A.I.M. Racing</title>
    <version os="Windows">
      <locations>
        <path ev="userdocuments" path="My Games\A.I.M. Racing"/>
        <registry root="local_machine" key="SOFTWARE\1C:Multimedia\A.I.M. Racing\Path" value="1"/>
      </locations>
      <files>
        <include>
          <exclude path="My Music"/>
        </include>
      </files>
      <linkable/>
      <contributor>AdmiringWorm</contributor>
    </version>
  </game>
  <game name="AirConflictsSecretWars" added="1955-11-05T00:00:00" updated="1955-11-05T00:00:00">
    <title>Air Conflicts Secret Wars</title>
    <version os="Windows">
      <locations>
        <path ev="localappdata" path="bitComposer\AirConflictsSW"/>
      </locations>
      <files>
        <include/>
      </files>
      <linkable/>
      <contributor>GameSaveManager</contributor>
    </version>
  </game>
  <game name="AirForte" added="2014-02-22T23:29:12" updated="2014-02-22T23:29:12">
    <title>Air Forte</title>
    <version os="Windows">
      <locations>
        <path ev="installlocation" path="Air Forte"/>
        <path ev="steamcommon" path="airforte"/>
        <shortcut ev="startmenu" path="Programs\Air Forte\Air Forte.lnk" detract="data"/>
      </locations>
      <files>
        <include path="data\AirForteSaveData" filename="*.sav"/>
      </files>
      <files type="Settings">
        <include path="data\AirForteSaveData" filename="*settings.dat"/>
      </files>
      <contributor>GameSave.Info</contributor>
    </version>
  </game>
  <game name="AirlineTycoon2" added="2013-02-03T05:40:17" updated="2013-02-03T05:40:17">
    <title>Airline Tycoon 2</title>
    <version os="Windows">
      <locations>
        <path ev="userdocuments" path="Kalypso Media\Airline Tycoon 2"/>
      </locations>
      <files>
        <include/>
      </files>
      <linkable/>
      <contributor>GameSaveManager</contributor>
    </version>
  </game>
  <game name="AirportControlSimulator" added="2013-02-03T05:40:17" updated="2013-02-03T05:40:17">
    <title>Airport Control Simulator</title>
    <version os="Windows">
      <locations>
        <path ev="appdata" path="Airport Control Simulator"/>
      </locations>
      <files>
        <include/>
      </files>
      <linkable/>
      <contributor>GameSaveManager</contributor>
    </version>
  </game>
  <game name="AIWarFleetCommand" added="1955-11-05T00:00:00" updated="1955-11-05T00:00:00">
    <title>AI War: Fleet Command</title>
    <version os="Windows">
      <locations>
        <path ev="steamcommon" path="ai war fleet command"/>
      </locations>
      <files>
        <include path="Save"/>
      </files>
      <linkable path="Save"/>
      <contributor>GameSave.Info</contributor>
    </version>
  </game>
  <game name="AladdinAndTheWonderfulLampThe1001Nights" added="2013-02-03T05:40:17" updated="2013-02-03T05:40:17">
    <title>Aladdin and the Wonderful Lamp: The 1001 Nights</title>
    <version os="Windows">
      <locations>
        <path ev="appdata" path="HdO Adventure\Aladin"/>
      </locations>
      <files>
        <include/>
      </files>
      <linkable/>
      <contributor>GameSaveManager</contributor>
    </version>
  </game>
  <game name="Alamandi" added="1955-11-05T00:00:00" updated="1955-11-05T00:00:00">
    <title>Alamandi</title>
    <version os="Windows">
      <locations>
        <path ev="localappdata" path="bitComposer\AirConflictsSW"/>
      </locations>
      <files>
        <include/>
      </files>
      <linkable/>
      <contributor>GameSaveManager</contributor>
    </version>
  </game>
  <game name="AlanWake" added="1955-11-05T00:00:00" updated="1955-11-05T00:00:00">
    <title>Alan Wake</title>
    <version platform="SteamCloud">
      <locations>
        <path ev="steamuserdata" path="108710"/>
      </locations>
      <files>
        <include/>
      </files>
      <contributor>Arc Angel</contributor>
    </version>
    <version os="Windows">
      <locations>
        <path ev="userdocuments" path="Remedy\AlanWake"/>
        <path ev="userdocuments" path="Remedy\AlanWake_GOG_Version"/>
      </locations>
      <files>
        <include path="savegames"/>
      </files>
      <files type="Settings">
        <include filename="*"/>
      </files>
      <linkable/>
      <contributor>GameSave.Info</contributor>
    </version>
  </game>
  <game name="AlanWakesAmericanNightmare" follows="AlanWake" added="1955-11-05T00:00:00" updated="1955-11-05T00:00:00">
    <title>Alan Wake's American Nightmare</title>
    <version platform="SteamCloud">
      <locations>
        <path ev="steamuserdata" path="202750"/>
      </locations>
      <files>
        <include/>
      </files>
      <contributor>Arc Angel</contributor>
    </version>
    <version os="Windows">
      <locations>
        <path ev="userdocuments" path="Remedy\AmericanNightmare"/>
        <path ev="userdocuments" path="Remedy\AmericanNightmare_GOG_Version"/>
      </locations>
      <files>
        <include path="savegames"/>
      </files>
      <files type="Settings">
        <include filename="*"/>
      </files>
      <linkable/>
      <contributor>GameSave.Info</contributor>
    </version>
  </game>
  <game name="Algodoo" added="2013-02-03T05:40:17" updated="2013-02-03T05:40:17">
    <title>Algodoo</title>
    <version os="Windows">
      <locations>
        <path ev="userdocuments" path="Algodoo"/>
      </locations>
      <files>
        <include/>
      </files>
      <linkable/>
      <contributor>GameSaveManager</contributor>
    </version>
  </game>
  <game name="Alice" added="1955-11-05T00:00:00" updated="1955-11-05T00:00:00">
    <title>American McGee's Alice</title>
    <version os="Windows">
      <locations>
        <path ev="installlocation" path="EA GAMES\American McGee's Alice"/>
        <registry root="local_machine" key="SOFTWARE\Microsoft\Windows\CurrentVersion\App Paths\Alice.exe" value="Path"/>
      </locations>
      <files>
        <include path="Base\save"/>
      </files>
      <files type="Settings">
        <include path="Base" filename="*.cfg"/>
      </files>
      <linkable path="Base\save"/>
      <contributor>GameSave.Info</contributor>
    </version>
  </game>
  <game name="AliceMadnessReturns" follows="Alice" added="1955-11-05T00:00:00" updated="1955-11-05T00:00:00">
    <title>Alice: Madness Returns</title>
    <version os="Windows">
      <locations>
        <path ev="userdocuments" path="My Games\Alice Madness Returns"/>
        <path ev="userdocuments" path="My Games\Alice Retour au pays de la folie"/>
      </locations>
      <files>
        <include path="AliceGame\CheckPoint"/>
      </files>
      <files type="Settings">
        <include path="AliceGame\Config"/>
      </files>
      <linkable/>
      <contributor>Arc Angel</contributor>
    </version>
  </game>
  <game name="AlienBreed2Assault" added="1955-11-05T00:00:00" updated="1955-11-05T00:00:00">
    <title>Alien Breed 2: Assault</title>
    <version os="Windows">
      <locations>
        <path ev="userdocuments" path="My Games\UnrealEngine3\AlienBreed2AssaultGame"/>
      </locations>
      <files>
        <include path="SaveData"/>
      </files>
      <files type="Settings">
        <include path="Config"/>
      </files>
      <linkable/>
      <contributor>Arc Angel</contributor>
    </version>
  </game>
  <game name="AlienBreed3Descent" follows="AlienBreed2Assault" added="1955-11-05T00:00:00" updated="1955-11-05T00:00:00">
    <title>Alien Breed 3: Descent</title>
    <version os="Windows">
      <locations>
        <path ev="userdocuments" path="My Games\UnrealEngine3\AlienBreed3DescentGame"/>
      </locations>
      <files>
        <include path="SaveData"/>
      </files>
      <files type="Settings">
        <include path="Config"/>
      </files>
      <linkable/>
      <contributor>Arc Angel</contributor>
    </version>
  </game>
  <game name="AlienBreedImpact" follows="AlienBreed3Descent" added="1955-11-05T00:00:00" updated="1955-11-05T00:00:00">
    <title>Alien Breed: Impact</title>
    <version os="Windows">
      <locations>
        <path ev="userdocuments" path="My Games\UnrealEngine3\AlienBreedEp1Game"/>
      </locations>
      <files>
        <include path="SaveData"/>
      </files>
      <files type="Settings">
        <include path="Config"/>
      </files>
      <linkable/>
      <contributor>Arc Angel</contributor>
    </version>
  </game>
  <game name="AlienHallway" added="1955-11-05T00:00:00" updated="1955-11-05T00:00:00">
    <title>Alien Hallway</title>
    <version os="Windows">
      <locations>
        <path ev="userdocuments" path="Sigma Team\Alien Hallway"/>
      </locations>
      <files>
        <include/>
      </files>
      <linkable/>
      <contributor>GameSaveManager</contributor>
    </version>
  </game>
  <game name="AliensColonialMarines" added="2013-02-23T21:39:00" updated="2013-02-23T21:39:00">
    <title>Aliens: Colonial Marines</title>
    <version platform="SteamCloud">
      <locations>
        <path ev="steamuserdata" path="49540"/>
      </locations>
      <files>
        <include/>
      </files>
      <contributor>Arc Angel</contributor>
    </version>
    <version os="Windows">
      <locations>
        <path ev="userdocuments" path="My Games\Aliens Colonial Marines"/>
      </locations>
      <files>
        <include/>
      </files>
      <linkable/>
      <contributor>GameSaveManager</contributor>
    </version>
  </game>
  <game name="AlienShooter2" added="1955-11-05T00:00:00" updated="1955-11-05T00:00:00">
    <title>Alien Shooter: Vengeance</title>
    <version os="Windows">
      <locations>
        <path ev="userdocuments" path="AlienShooter2 Saves"/>
      </locations>
      <files>
        <include/>
      </files>
      <linkable/>
      <contributor>GameSave.Info</contributor>
    </version>
    <version os="Windows" release="Reloaded">
      <title>Alien Shooter 2: Reloaded</title>
      <locations>
        <path ev="userdocuments" path="AlienShooter2 Reloaded Saves"/>
      </locations>
      <files>
        <include/>
      </files>
      <linkable/>
      <contributor>Arc Angel</contributor>
    </version>
  </game>
  <game name="AlienShooterRevisited" added="1955-11-05T00:00:00" updated="1955-11-05T00:00:00">
    <title>Alien Shooter: Revisited</title>
    <version os="Windows">
      <locations>
        <path ev="userdocuments" path="AlienShooter Revisited Saves"/>
      </locations>
      <files>
        <include/>
      </files>
      <linkable/>
      <contributor>GameSaveManager</contributor>
    </version>
  </game>
  <game name="AliensVsPredator" added="1955-11-05T00:00:00" updated="1955-11-05T00:00:00">
    <title>Aliens vs. Predator</title>
    <version platform="SteamCloud" release="Classic">
      <title>Aliens vs. Predator Classic</title>
      <locations>
        <path ev="steamuserdata" path="10680"/>
      </locations>
      <files>
        <include/>
      </files>
      <contributor>GameSaveManager</contributor>
    </version>
    <version os="Windows" release="Classic">
      <title>Aliens vs. Predator Classic</title>
      <locations>
        <path ev="localappdata" path="Rebellion\AvP Classic"/>
      </locations>
      <files>
        <include/>
      </files>
      <linkable/>
      <contributor>GameSave.Info</contributor>
    </version>
  </game>
  <game name="AliensVsPredator2" added="1955-11-05T00:00:00" updated="1955-11-05T00:00:00">
    <title>Aliens vs. Predator 2</title>
    <version os="Windows">
      <locations>
        <path ev="installlocation" path="Fox\Aliens vs. Predator 2"/>
        <registry root="local_machine" key="SOFTWARE\Monolith Productions\Aliens vs. Predator 2\1.0" value="InstallDir"/>
        <registry root="local_machine" key="SOFTWARE\Sierra OnLine\Setup\AVP2" value="Directory"/>
        <shortcut ev="startmenu" path="Programs\Fox Interactive\Aliens vs. Predator 2\Aliens vs. Predator 2.lnk"/>
      </locations>
      <files>
        <include path="Profiles"/>
        <include path="Save"/>
      </files>
      <linkable path="Profiles"/>
      <linkable path="Save"/>
      <contributor>GameSave.Info</contributor>
    </version>
  </game>
  <game name="AliensVsPredator2010" follows="AliensVsPredator2" added="1955-11-05T00:00:00" updated="1955-11-05T00:00:00">
    <title>Aliens vs. Predator (2010)</title>
    <version os="Windows">
      <locations>
        <path ev="localappdata" path="AliensVsPredator"/>
      </locations>
      <files>
        <include/>
      </files>
      <linkable/>
      <contributor>Michael Lamere</contributor>
    </version>
  </game>
  <expansion name="AliensVsPredator2PrimalHunt" for="AliensVsPredator2" added="1955-11-05T00:00:00" updated="1955-11-05T00:00:00">
    <title>Aliens vs. Predator 2: Primal Hunt</title>
    <version os="Windows">
      <locations>
        <path ev="installlocation" path="Fox\Aliens versus Predator 2 - Primal Hunt"/>
        <registry root="local_machine" key="SOFTWARE\Sierra OnLine\Setup\AVP2X" value="Directory"/>
        <registry root="local_machine" key="SOFTWARE\Third Law Interactive\Aliens versus Predator 2: Primal Hunt\1.0" value="InstallDir"/>
        <shortcut ev="startmenu" path="Programs\Fox Interactive\Aliens versus Predator 2 - Primal Hunt\Aliens versus Predator 2 - Primal Hunt.lnk"/>
      </locations>
      <files>
        <include path="Profiles"/>
        <include path="Save"/>
      </files>
      <linkable path="Profiles"/>
      <linkable path="Save"/>
      <contributor>GameSave.Info</contributor>
    </version>
  </expansion>
  <game name="AlienSwarm" added="1955-11-05T00:00:00" updated="1955-11-05T00:00:00">
    <title>Alien Swarm</title>
    <version platform="SteamCloud">
      <locations>
        <path ev="steamuserdata" path="630"/>
      </locations>
      <files>
        <include/>
      </files>
      <contributor>AvvA</contributor>
    </version>
    <version os="Windows">
      <locations>
        <path ev="steamcommon" path="alien swarm"/>
      </locations>
      <files type="Settings">
        <include path="swarm\cfg"/>
      </files>
      <contributor>GameSaveManager</contributor>
    </version>
  </game>
  <game name="AllZombiesMustDie" added="2012-08-27T18:13:36" updated="2012-08-27T18:13:36">
    <title>All Zombies Must Die!</title>
    <version os="Windows">
      <locations>
        <path ev="userdocuments" path="My Games\UnrealEngine3\Bzb2Game"/>
      </locations>
      <files>
        <include>
          <exclude filename="Logs"/>
        </include>
      </files>
      <linkable/>
      <contributor>GameSaveManager</contributor>
    </version>
  </game>
  <game name="AloneInTheDark" added="1955-11-05T00:00:00" updated="1955-11-05T00:00:00">
    <title>Alone in the Dark</title>
    <version os="DOS">
      <locations>
        <path ev="installlocation" path="GOG.com\Alone in the Dark\INDARK"/>
        <registry root="local_machine" key="SOFTWARE\GOG.com\GOGALONE1" value="PATH" append="INDARK"/>
        <shortcut ev="startmenu" path="Programs\GOG.com\Alone in the Dark\Alone in the Dark.lnk" detract="DOSBOX" append="INDARK"/>
      </locations>
      <files>
        <include filename="SAVE?.ITD"/>
      </files>
      <contributor>GameSave.Info</contributor>
    </version>
  </game>
  <game name="AloneInTheDark2" follows="AloneInTheDark" added="1955-11-05T00:00:00" updated="1955-11-05T00:00:00">
    <title>Alone in the Dark 2</title>
    <version os="DOS">
      <locations>
        <path ev="installlocation" path="GOG.com\Alone in the Dark 2\INDARK2"/>
        <registry root="local_machine" key="SOFTWARE\GOG.com\GOGALONE2" value="PATH" append="INDARK2"/>
        <shortcut ev="startmenu" path="Programs\GOG.com\Alone in the Dark 2\Alone in the Dark 2.lnk" detract="DOSBOX" append="INDARK2"/>
      </locations>
      <files>
        <include filename="SAVE?.ITD"/>
      </files>
      <contributor>GameSave.Info</contributor>
    </version>
  </game>
  <game name="AloneInTheDark2008" added="1955-11-05T00:00:00" updated="1955-11-05T00:00:00">
    <title>Alone in the Dark (2008)</title>
    <version os="Windows">
      <locations>
        <path ev="localappdata" path="Atari\AITD"/>
      </locations>
      <files>
        <include/>
      </files>
      <linkable/>
      <contributor>GameSaveManager</contributor>
    </version>
  </game>
  <game name="AloneInTheDark3" follows="AloneInTheDark2" added="1955-11-05T00:00:00" updated="1955-11-05T00:00:00">
    <title>Alone in the Dark 3</title>
    <version os="DOS">
      <locations>
        <path ev="installlocation" path="GOG.com\Alone in the Dark 3\INDARK3"/>
        <registry root="local_machine" key="SOFTWARE\GOG.com\GOGALONE3" value="PATH" append="INDARK3"/>
        <shortcut ev="startmenu" path="Programs\GOG.com\Alone in the Dark 3\Alone in the Dark 3.lnk" detract="DOSBOX" append="INDARK3"/>
      </locations>
      <files>
        <include path="SAVE??" filename="SAVE?.ITD"/>
      </files>
      <contributor>GameSave.Info</contributor>
    </version>
  </game>
  <game name="AloneInTheDarkTheNewNightmare" follows="AloneInTheDark3" added="1955-11-05T00:00:00" updated="1955-11-05T00:00:00">
    <title>Alone in the Dark: The New Nightmare</title>
    <version os="Windows">
      <locations>
        <path ev="installlocation" path="GOG.com\Alone in the Dark - The New Nightmare"/>
        <registry root="local_machine" key="SOFTWARE\GOG.com\GOGALONEINTHEDARK" value="PATH"/>
        <shortcut ev="startmenu" path="Programs\GOG.com\Alone in the Dark - The New Nightmare\Alone in the Dark - The New Nightmare.lnk"/>
      </locations>
      <files>
        <include filename="*.sav"/>
      </files>
      <contributor>GameSave.Info</contributor>
    </version>
  </game>
  <game name="AlphaCentauri" added="1955-11-05T00:00:00" updated="1955-11-05T00:00:00">
    <title>Sid Meier's Alpha Centauri</title>
    <version os="Windows">
      <locations>
        <path ev="installlocation" path="Firaxis Games\Sid Meier's Alpha Centauri"/>
        <path ev="installlocation" path="GOG.com\Sid Meiers Alpha Centauri"/>
        <path ev="installlocation" path="GOGcom\Sid Meiers Alpha Centauri"/>
        <registry root="local_machine" key="SOFTWARE\GOG.com\GOGSIDMAIERSALPHACENTAURI" value="PATH"/>
        <registry root="local_machine" key="SOFTWARE\Microsoft\DirectPlay\Applications\Sid Meier's Alpha Centauri" value="Path"/>
        <shortcut ev="startmenu" path="Programs\GOG.com\Sid Meier's Alpha Centauri\Sid Meier's Alpha Centauri.lnk"/>
      </locations>
      <files>
        <include filename="*.SAV"/>
        <include path="saves"/>
      </files>
      <files type="Maps">
        <include path="maps" modified_after="2000-01-01T00:00:00"/>
      </files>
      <files type="Scenarios">
        <include path="scenarios" modified_after="2000-01-01T00:00:00"/>
      </files>
      <files type="Settings">
        <include filename="Alpha Centauri.Ini"/>
      </files>
      <linkable path="saves"/>
      <contributor>GameSave.Info</contributor>
    </version>
  </game>
  <game name="AlphaPrime" added="1955-11-05T00:00:00" updated="1955-11-05T00:00:00">
    <title>Alpha Prime</title>
    <version os="Windows">
      <locations>
        <path ev="steamcommon" path="alpha prime"/>
        <registry root="local_machine" key="SOFTWARE\Microsoft\Windows\CurrentVersion\Uninstall\Alpha Prime" value="InstallLocation"/>
      </locations>
      <files>
        <include path="save"/>
      </files>
      <files type="Settings">
        <include filename="settings.cfg"/>
      </files>
      <linkable path="save"/>
      <contributor>GameSaveManager</contributor>
    </version>
  </game>
  <game name="AlphaProtocol" added="1955-11-05T00:00:00" updated="1955-11-05T00:00:00">
    <title>Alpha Protocol</title>
    <version os="Windows">
      <locations>
        <path ev="userdocuments" path="Alpha Protocol"/>
      </locations>
      <files>
        <include path="Checkpoints"/>
        <include path="Profile"/>
      </files>
      <files type="Settings">
        <include path="APGame\Config"/>
      </files>
      <linkable/>
      <contributor>Arc Angel</contributor>
    </version>
  </game>
  <game name="AlterEcho" added="1955-11-05T00:00:00" updated="1955-11-05T00:00:00">
    <title>Alter Echo</title>
    <version os="PS2" region="USA">
      <ps_code prefix="SLUS" suffix="20465"/>
      <contributor>GameSave.Info</contributor>
    </version>
  </game>
  <game name="AlternativA" added="1955-11-05T00:00:00" updated="1955-11-05T00:00:00">
    <title>AlternativA</title>
    <version platform="SteamCloud">
      <locations>
        <path ev="steamuserdata" path="33990"/>
      </locations>
      <files>
        <include/>
      </files>
      <contributor>AdmiringWorm</contributor>
    </version>
  </game>
  <game name="Altitude" added="1955-11-05T00:00:00" updated="1955-11-05T00:00:00">
    <title>Altitude</title>
    <version>
      <locations>
        <path ev="steamcommon" path="Altitude"/>
      </locations>
      <files type="Settings">
        <include path="config"/>
      </files>
      <contributor>AvvA</contributor>
    </version>
  </game>
  <game name="AmazingSpiderMan" added="2013-02-03T05:40:17" updated="2013-02-03T05:40:17">
    <title>The Amazing Spider-Man</title>
    <version platform="SteamCloud">
      <locations>
        <path ev="steamuserdata" path="212580"/>
      </locations>
      <files>
        <include/>
      </files>
      <contributor>GameSaveManager</contributor>
    </version>
    <version os="Windows">
      <locations>
        <path ev="userdocuments" path="Activision\ASM"/>
      </locations>
      <files>
        <include/>
      </files>
      <linkable/>
      <contributor>GameSaveManager</contributor>
    </version>
  </game>
  <game name="AmericasArmy3" added="2013-02-03T05:40:17" updated="2013-02-03T05:40:17">
    <title>America's Army 3</title>
    <version os="Windows">
      <locations>
        <registry root="local_machine" key="SOFTWARE\US Army\America's Army\AA3Client" value="installdir"/>
      </locations>
      <files>
        <include path="AA3Game\Config"/>
      </files>
      <contributor>GameSaveManager</contributor>
    </version>
  </game>
  <game name="AmerzoneTheExplorersLegacy" added="1955-11-05T00:00:00" updated="1955-11-05T00:00:00">
    <title>Amerzone: The Explorer's Legacy</title>
    <version os="Windows">
      <locations>
        <path ev="installlocation" path="GOG.com\AmerZone"/>
        <registry root="local_machine" key="SOFTWARE\GOG.com\GOGAMERZONE" value="PATH"/>
        <registry root="local_machine" key="SOFTWARE\GOG.com\GOGAMERZONEUS" value="PATH"/>
        <registry root="local_machine" key="SOFTWARE\Microfolie's\L'Amerzone\1.0" value="res"/>
        <registry root="local_machine" key="SOFTWARE\Microfolie's\L'Amerzone\1.0" value="source"/>
        <shortcut ev="startmenu" path="Programs\GOG.com\AmerZone - The Explorer's Legacy\AmerZone - The Explorer's Legacy.lnk"/>
      </locations>
      <files>
        <include filename="Saved_*.bin"/>
      </files>
      <contributor>GameSave.Info</contributor>
    </version>
  </game>
  <game name="AmnesiaTheDarkDescent" added="1955-11-05T00:00:00" updated="1955-11-05T00:00:00">
    <title>Amnesia: The Dark Descent</title>
    <version os="Windows">
      <locations>
        <path ev="userdocuments" path="Amnesia"/>
      </locations>
      <files>
        <include path="Main" filename="*.cfg"/>
        <include path="Main\*"/>
      </files>
      <linkable/>
      <contributor>Arc Angel</contributor>
    </version>
  </game>
  <game name="Anachronox" added="1955-11-05T00:00:00" updated="2012-10-01T16:54:44">
    <title>Anachronox</title>
    <version os="Windows">
      <locations>
        <path ev="installlocation" path="Anachronox"/>
        <path ev="installlocation" path="GOG.com\Anachronox"/>
        <registry root="local_machine" key="SOFTWARE\Eidos Interactive\Anachronox" value="SourcePath"/>
        <registry root="local_machine" key="SOFTWARE\GOG.com\GOGANACHRONOX" value="PATH"/>
        <shortcut ev="startmenu" path="Programs\Eidos Interactive\Anachronox\Anachronox.lnk"/>
        <shortcut ev="startmenu" path="Programs\GOG.com\Anachronox\Anachronox.lnk"/>
      </locations>
      <files>
        <include path="anoxdata\SAVE"/>
      </files>
      <linkable path="anoxdata\SAVE"/>
      <contributor>GameSave.Info</contributor>
    </version>
  </game>
  <game name="AnalogueAHateStory" added="1955-11-05T00:00:00" updated="1955-11-05T00:00:00">
    <title>Analogue: A Hate Story</title>
    <version platform="RenPy">
      <locations>
        <path ev="userdocuments" path="RenPy\Analogue"/>
      </locations>
      <files>
        <include/>
      </files>
      <linkable/>
      <contributor>GameSaveManager</contributor>
    </version>
  </game>
  <game name="AndYetItMoves" added="1955-11-05T00:00:00" updated="1955-11-05T00:00:00">
    <title>And Yet It Moves</title>
    <version os="Windows">
      <locations>
        <path ev="appdata" path="Broken Rules\And Yet It Moves Greenhouse"/>
        <path ev="appdata" path="Broken Rules\And Yet It Moves Steam"/>
      </locations>
      <files>
        <include>
          <exclude filename="console.log"/>
        </include>
      </files>
      <linkable/>
      <contributor>GameSaveManager</contributor>
    </version>
  </game>
  <game name="ANewBeginning" added="1955-11-05T00:00:00" updated="1955-11-05T00:00:00">
    <title>A New Beginning</title>
    <version os="Windows">
      <locations>
        <path ev="localappdata" path="Daedalic Entertainment\A New Beginning"/>
      </locations>
      <files>
        <include/>
      </files>
      <linkable/>
      <contributor>GameSaveManager</contributor>
    </version>
  </game>
  <game name="AngelsOnline" added="1955-11-05T00:00:00" updated="2013-01-05T16:19:39">
    <title>Angels Online</title>
    <version os="Windows">
      <locations>
        <path ev="installlocation" path="Angels Online"/>
        <registry root="local_machine" key="SOFTWARE\IGG Games\Angels Online\Settings" value="Path"/>
        <shortcut ev="startmenu" path="Programs\Angels Online\Angels Online.lnk"/>
      </locations>
      <files>
        <include path="save\data"/>
      </files>
      <files type="Settings">
        <include path="midage.ini"/>
        <include path="save\cfg"/>
      </files>
      <contributor>AdmiringWorm</contributor>
    </version>
  </game>
  <game name="AngryBirds" added="1955-11-05T00:00:00" updated="1955-11-05T00:00:00">
    <title>Angry Birds</title>
    <version os="Windows">
      <locations>
        <path ev="appdata" path="Rovio\Angry Birds"/>
      </locations>
      <files>
        <include/>
      </files>
      <linkable/>
      <contributor>GameSaveManager</contributor>
    </version>
  </game>
  <game name="AngryBirdsRio" added="1955-11-05T00:00:00" updated="1955-11-05T00:00:00">
    <title>Angry Birds Rio</title>
    <version os="Windows">
      <locations>
        <path ev="appdata" path="Rovio\Angry Birds Rio"/>
      </locations>
      <files>
        <include/>
      </files>
      <linkable/>
      <contributor>GameSaveManager</contributor>
    </version>
  </game>
  <game name="AngryBirdsSeasons" added="1955-11-05T00:00:00" updated="1955-11-05T00:00:00">
    <title>Angry Birds Seasons</title>
    <version os="Windows">
      <locations>
        <path ev="appdata" path="Rovio\Angry Birds Seasons"/>
      </locations>
      <files>
        <include/>
      </files>
      <linkable/>
      <contributor>GameSaveManager</contributor>
    </version>
  </game>
  <game name="AngryBirdsSpace" added="1955-11-05T00:00:00" updated="1955-11-05T00:00:00">
    <title>Angry Birds Space</title>
    <version os="Windows">
      <locations>
        <path ev="appdata" path="Rovio\Angry Birds Space"/>
      </locations>
      <files type="Highscores">
        <include filename="highscores.lua"/>
      </files>
      <files type="Settings">
        <include filename="settings.lua"/>
      </files>
      <linkable/>
      <contributor>cheshhire</contributor>
    </version>
  </game>
  <game name="AnimalColorCross" added="2013-06-14T05:17:42" updated="2013-06-14T05:17:42">
    <title>Animal Color Cross</title>
    <version os="Windows">
      <locations>
        <path ev="appdata" path="Little Worlds Online\AnimalColorCross"/>
      </locations>
      <files>
        <include/>
      </files>
      <linkable/>
      <contributor>GameSaveManager</contributor>
    </version>
  </game>
  <game name="Ankh2HeartOfOsiris" added="1955-11-05T00:00:00" updated="1955-11-05T00:00:00">
    <title>Ankh 2: Heart of Osiris</title>
    <version os="Windows">
      <locations>
        <path ev="appdata" path="Ankh - Heart of Osiris"/>
      </locations>
      <files>
        <include/>
      </files>
      <linkable/>
      <contributor>GameSaveManager</contributor>
    </version>
  </game>
  <game name="Ankh3BattleOfTheGods" added="1955-11-05T00:00:00" updated="1955-11-05T00:00:00">
    <title>Ankh 3: Battle of the Gods</title>
    <version os="Windows">
      <locations>
        <path ev="userdocuments" path="Ankh - Battle of the Gods"/>
      </locations>
      <files>
        <include/>
      </files>
      <linkable/>
      <contributor>GameSaveManager</contributor>
    </version>
  </game>
  <game name="Anna" added="2012-10-01T16:54:44" updated="2012-10-01T16:54:44">
    <title>Anna</title>
    <version os="Windows">
      <locations>
        <path ev="userprofile" path="AppData\LocalLow\Dreampainters\Anna"/>
      </locations>
      <files>
        <include/>
      </files>
      <linkable/>
      <contributor>GameSaveManager</contributor>
    </version>
  </game>
  <game name="Anno1404" added="1955-11-05T00:00:00" updated="1955-11-05T00:00:00">
    <title>Anno 1404</title>
    <version os="Windows">
      <locations>
        <path ev="userdocuments" path="Anno 1404"/>
      </locations>
      <files>
        <include path="Savegames"/>
      </files>
      <linkable/>
      <contributor>Caleb Love</contributor>
    </version>
  </game>
  <game name="Anno1404DawnOfDiscovery" added="2013-02-03T05:40:17" updated="2013-02-03T05:40:17">
    <title>Anno 1404: Dawn of Discovery</title>
    <version os="Windows">
      <locations>
        <path ev="userdocuments" path="Dawn of Discovery"/>
      </locations>
      <files>
        <include/>
      </files>
      <linkable/>
      <contributor>GameSaveManager</contributor>
    </version>
  </game>
  <game name="Anno1404Venice" added="2013-02-03T05:40:17" updated="2013-02-03T05:40:17">
    <title>Anno 1404: Venice</title>
    <version os="Windows">
      <locations>
        <path ev="appdata" path="Ubisoft\Anno1404Addon"/>
        <path ev="userdocuments" path="Anno 1404 Venedig"/>
        <path ev="userdocuments" path="Anno 1404 Venice"/>
      </locations>
      <files>
        <include/>
      </files>
      <linkable/>
      <contributor>GameSaveManager</contributor>
    </version>
  </game>
  <game name="Anno2070" added="1955-11-05T00:00:00" updated="1955-11-05T00:00:00">
    <title>Anno 2070</title>
    <version os="Windows">
      <locations>
        <path ev="userdocuments" path="ANNO 2070"/>
      </locations>
      <files>
        <include>
          <exclude path="Cache"/>
          <exclude path="Config\fxo"/>
          <exclude path="Logs"/>
        </include>
      </files>
      <linkable/>
      <contributor>isshunfuran</contributor>
    </version>
  </game>
  <game name="Anodyne" added="2013-06-14T05:17:42" updated="2013-06-14T05:17:42">
    <title>Anodyne</title>
    <version os="Windows">
      <locations>
        <path ev="appdata" path="Anodyne"/>
      </locations>
      <files>
        <include/>
      </files>
      <linkable/>
      <contributor>GameSaveManager</contributor>
    </version>
  </game>
  <game name="Anomaly2" added="2014-02-22T23:29:12" updated="2014-02-22T23:29:12">
    <title>Anomaly 2</title>
    <version platform="SteamCloud">
      <locations>
        <path ev="steamuserdata" path="236730"/>
      </locations>
      <files>
        <include/>
      </files>
      <contributor>GameSave.Info</contributor>
    </version>
    <version os="Windows">
      <locations>
        <path ev="appdata" path="11bitstudios\Anomaly 2"/>
      </locations>
      <files>
        <include/>
      </files>
      <linkable/>
      <contributor>GameSave.Info</contributor>
    </version>
  </game>
  <game name="AnomalyKorea" added="2014-02-22T23:29:12" updated="2014-02-22T23:29:12">
    <title>Anomaly Korea</title>
    <version os="Windows">
      <locations>
        <path ev="userdocuments" path="Anomaly Korea"/>
      </locations>
      <files>
        <include/>
      </files>
      <linkable/>
      <contributor>GameSave.Info</contributor>
    </version>
  </game>
  <game name="AnomalyWarzoneEarth" added="1955-11-05T00:00:00" updated="1955-11-05T00:00:00">
    <title>Anomaly: Warzone Earth</title>
    <version platform="SteamCloud">
      <locations>
        <path ev="steamuserdata" path="91200"/>
      </locations>
      <files>
        <include/>
      </files>
      <contributor>Arc Angel</contributor>
    </version>
    <version os="Windows">
      <locations>
        <path ev="userdocuments" path="Anomaly Warzone Earth"/>
      </locations>
      <files>
        <include/>
      </files>
      <linkable/>
      <contributor>GameSaveManager</contributor>
    </version>
  </game>
  <game name="AnotherWorld" added="1955-11-05T00:00:00" updated="1955-11-05T00:00:00">
    <title>Another World</title>
    <version os="Windows">
      <locations>
        <registry root="local_machine" key="SOFTWARE\GOG.com\GOGANOTHERWORLD" value="PATH"/>
      </locations>
      <files>
        <include filename="AnotherWorld.ini"/>
      </files>
      <contributor>GameSaveManager</contributor>
    </version>
  </game>
  <game name="Antichamber" added="2013-06-14T05:17:42" updated="2013-06-14T05:17:42">
    <title>Antichamber</title>
    <version os="Windows">
      <locations>
        <path ev="steamcommon" path="Antichamber"/>
      </locations>
      <files>
        <include path="Binaries\Win32" filename="SavedGame.bin"/>
      </files>
      <contributor>GameSaveManager</contributor>
    </version>
  </game>
  <game name="ApacheAirAssault" added="2013-02-03T05:40:17" updated="2013-02-03T05:40:17">
    <title>Apache: Air Assault</title>
    <version os="Windows">
      <locations>
        <path ev="userdocuments" path="My Games\Apache"/>
      </locations>
      <files>
        <include/>
      </files>
      <linkable/>
      <contributor>GameSaveManager</contributor>
    </version>
  </game>
  <game name="APBReloaded" added="1955-11-05T00:00:00" updated="2013-01-05T16:19:39">
    <title>APB Reloaded</title>
    <version os="Windows">
      <locations>
        <path ev="installlocation" path="GamersFirst\APB Reloaded"/>
        <path ev="steamcommon" path="apb reloaded"/>
        <registry root="local_machine" key="SOFTWARE\GamersFirst\APB\APB Reloaded" value="Installation Path"/>
        <registry root="local_machine" key="SOFTWARE\Microsoft\Windows\CurrentVersion\Uninstall\Steam App 113400" value="InstallLocation"/>
        <shortcut ev="startmenu" path="Programs\GamersFirst\APB Reloaded\APB Reloaded.lnk" detract="Launcher"/>
      </locations>
      <files type="Accounts">
        <include path="APBGame\Config\Account"/>
      </files>
      <files type="Settings">
        <include path="APBGame\Config" filename="*.ini"/>
        <include path="APBGame\Config\Linux"/>
      </files>
      <contributor>AdmiringWorm</contributor>
    </version>
  </game>
  <game name="APOX" added="1955-11-05T00:00:00" updated="1955-11-05T00:00:00">
    <title>APOX</title>
    <version os="Windows">
      <locations>
        <path ev="userdocuments" path="APOX\Save"/>
      </locations>
      <files>
        <include/>
      </files>
      <linkable/>
      <contributor>GameSaveManager</contributor>
    </version>
  </game>
  <game name="Aquanox" added="1955-11-05T00:00:00" updated="1955-11-05T00:00:00">
    <title>Aquanox</title>
    <version os="Windows">
      <locations>
        <path ev="appdata" path="AquaNox"/>
      </locations>
      <files>
        <include filename="player*"/>
      </files>
      <linkable/>
      <contributor>GameSave.Info</contributor>
    </version>
  </game>
  <game name="Aquanox2" follows="Aquanox" added="1955-11-05T00:00:00" updated="1955-11-05T00:00:00">
    <title>Aquanox 2: Revelation</title>
    <version os="Windows">
      <locations>
        <path ev="userdocuments" path="AquaNox2"/>
      </locations>
      <files>
        <include filename="*.an2"/>
      </files>
      <files type="Settings">
        <include filename="Config.txt"/>
      </files>
      <linkable/>
      <contributor>GameSave.Info</contributor>
    </version>
  </game>
  <game name="Aquaria" added="1955-11-05T00:00:00" updated="2013-01-05T16:19:39">
    <title>Aquaria</title>
    <version os="Windows">
      <locations>
        <path ev="installlocation" path="Aquaria"/>
        <path ev="steamcommon" path="aquaria"/>
        <registry root="local_machine" key="SOFTWARE\BITBLOT_Aquaria" value="Install_Dir"/>
        <registry root="local_machine" key="SOFTWARE\Microsoft\Windows\CurrentVersion\Uninstall\Steam App 24420" value="InstallLocation"/>
        <shortcut ev="startmenu" path="Programs\Aquaria\Aquaria.lnk"/>
      </locations>
      <files>
        <include path="save"/>
      </files>
      <files type="Screenshots">
        <include path="screenshots"/>
      </files>
      <files type="Settings">
        <include filename="usersettings.xml"/>
      </files>
      <linkable path="save"/>
      <contributor>AdmiringWorm</contributor>
      <contributor>Dwight Holman</contributor>
      <contributor>slake_jones</contributor>
    </version>
  </game>
  <game name="ArcaniaFallOfSetarrif" added="1955-11-05T00:00:00" updated="1955-11-05T00:00:00">
    <title>ArcaniA: Fall of Setarrif</title>
    <version os="Windows">
      <locations>
        <path ev="userdocuments" path="ArcaniA - AddOn"/>
      </locations>
      <files>
        <include/>
      </files>
      <linkable/>
      <contributor>Arc Angel</contributor>
    </version>
  </game>
  <game name="ArcaniaGothic4" added="1955-11-05T00:00:00" updated="1955-11-05T00:00:00">
    <title>ArcaniA: Gothic 4</title>
    <version os="Windows">
      <locations>
        <path ev="userdocuments" path="ArcaniA - Gothic 4"/>
      </locations>
      <files>
        <include/>
      </files>
      <linkable/>
      <contributor>Arc Angel</contributor>
    </version>
  </game>
  <game name="ArcanumOfSteamworksAndMagickObscura" added="1955-11-05T00:00:00" updated="1955-11-05T00:00:00">
    <title>Arcanum: Of Steamworks and Magick Obscura</title>
    <version os="Windows">
      <locations>
        <path ev="installlocation" path="GOG.com\Arcanum"/>
        <registry root="local_machine" key="SOFTWARE\GOG.com\GOGARCANUM" value="PATH"/>
        <registry root="local_machine" key="SOFTWARE\Sierra OnLine\Setup\AR_USENG" value="Directory"/>
        <registry root="local_machine" key="SOFTWARE\Troika\Arcanum" value="installed_to"/>
        <shortcut ev="startmenu" path="Programs\GOG.com\Arcanum Of Steamworks and Magick Obscura\Arcanum Of Steamworks and Magick Obscura.lnk"/>
      </locations>
      <files>
        <include path="modules\Arcanum\Save" filename="*"/>
      </files>
      <linkable path="modules\Arcanum\Save"/>
      <contributor>GameSave.Info</contributor>
    </version>
  </game>
  <game name="ArchibaldsAdventures" added="2013-02-03T05:40:17" updated="2013-02-03T05:40:17">
    <title>Archibald's Adventures</title>
    <version os="Windows">
      <locations>
        <path ev="appdata" path="Archibald's Adventures"/>
      </locations>
      <files>
        <include filename="*.sav"/>
        <include filename="game_config.txt"/>
      </files>
      <linkable/>
      <contributor>GameSaveManager</contributor>
    </version>
  </game>
  <game name="ArchonClassics" added="2013-02-03T05:40:17" updated="2013-02-03T05:40:17">
    <title>Archon Classics</title>
    <version os="Windows">
      <locations>
        <path ev="appdata" path="ReactGames\ArchonPC"/>
      </locations>
      <files>
        <include/>
      </files>
      <linkable/>
      <contributor>GameSaveManager</contributor>
    </version>
  </game>
  <game name="Area51" added="1955-11-05T00:00:00" updated="1955-11-05T00:00:00">
    <title>Area 51</title>
    <version os="Windows">
      <locations>
        <registry root="local_machine" key="SOFTWARE\Microsoft\Windows\CurrentVersion\Uninstall\AREA-51" value="DisplayIcon"/>
      </locations>
      <files>
        <include path="SAVES"/>
      </files>
      <linkable path="SAVES"/>
      <contributor>GameSaveManager</contributor>
    </version>
  </game>
  <game name="ARES" added="1955-11-05T00:00:00" updated="1955-11-05T00:00:00">
    <title>A.R.E.S</title>
    <version os="Windows">
      <locations>
        <path ev="userdocuments" path="ARES"/>
      </locations>
      <files>
        <include>
          <exclude filename="config.ini"/>
        </include>
      </files>
      <files type="Settings">
        <include filename="config.ini"/>
      </files>
      <linkable/>
      <contributor>Arc Angel</contributor>
    </version>
  </game>
  <game name="ArmA2" follows="ArmACombatOperations" added="1955-11-05T00:00:00" updated="1955-11-05T00:00:00">
    <title>ArmA II</title>
    <version os="Windows">
      <locations>
        <path ev="userdocuments" path="ArmA 2"/>
      </locations>
      <files>
        <include/>
      </files>
      <linkable/>
      <contributor>Arc Angel</contributor>
    </version>
  </game>
  <game name="ArmA2OperationArrowhead" added="2012-09-12T14:11:29" updated="2012-09-12T14:11:29">
    <title>ArmA II: Operation Arrowhead</title>
    <version os="Windows">
      <locations>
        <path ev="localappdata" path="ArmA 2 OA"/>
      </locations>
      <files>
        <include/>
      </files>
      <linkable/>
      <contributor>simtech76</contributor>
    </version>
  </game>
  <game name="ArmA2REINFORCEMENTS" added="2013-02-03T05:40:17" updated="2013-02-03T05:40:17">
    <title>ArmA 2: REINFORCEMENTS</title>
    <version os="Windows">
      <locations>
        <path ev="localappdata" path="ArmA 2 REINFORCEMENTS"/>
      </locations>
      <files>
        <include/>
      </files>
      <linkable/>
      <contributor>GameSaveManager</contributor>
    </version>
  </game>
  <game name="ArmAColdWarAssault" added="2013-02-23T21:39:00" updated="2013-02-23T21:39:00">
    <title>ArmA: Cold War Assault</title>
    <version os="Windows">
      <locations>
        <registry root="local_machine" key="SOFTWARE\Bohemia Interactive Studio\ColdWarAssault" value="MAIN"/>
      </locations>
      <files>
        <include path="Users"/>
      </files>
      <contributor>GameSaveManager</contributor>
    </version>
  </game>
  <game name="ArmACombatOperations" added="1955-11-05T00:00:00" updated="1955-11-05T00:00:00">
    <title>ArmA: Combat Operations</title>
    <version os="Windows">
      <locations>
        <path ev="userdocuments" path="ArmA"/>
      </locations>
      <files>
        <include/>
      </files>
      <linkable/>
      <contributor>Arc Angel</contributor>
    </version>
  </game>
  <game name="Armada2526" added="1955-11-05T00:00:00" updated="1955-11-05T00:00:00">
    <title>Armada 2526</title>
    <version os="Windows">
      <locations>
        <path ev="userdocuments" path="My Games\Armada 2526"/>
        <path ev="userdocuments" path="Saved Games\Armada 2526"/>
      </locations>
      <files>
        <include filename="*.2526sav"/>
      </files>
      <linkable/>
      <contributor>GameSave.Info</contributor>
    </version>
    <version os="Windows" release="Gold">
      <title>Armada 2526 Gold Edition</title>
      <locations>
        <path ev="userdocuments" path="My Games\Armada 2526 Gold"/>
      </locations>
      <files>
        <include/>
      </files>
      <linkable/>
      <contributor>GameSaveManager</contributor>
    </version>
  </game>
  <expansion name="Armada2526Supernova" for="Armada2526" added="1955-11-05T00:00:00" updated="1955-11-05T00:00:00">
    <title>Armada 2526: Supernova</title>
    <version os="Windows">
      <locations>
        <parent name="Armada2526" os="Windows" append="Supernova"/>
      </locations>
      <files>
        <include filename="*.2526sav"/>
      </files>
      <contributor>GameSave.Info</contributor>
    </version>
  </expansion>
  <game name="ArmedAndDangerous" added="2013-06-14T05:17:42" updated="2013-06-14T05:17:42">
    <title>Armed and Dangerous</title>
    <version os="Windows">
      <locations>
        <path ev="steamcommon" path="Armed and Dangerous"/>
      </locations>
      <files>
        <include path="GameData\SavedGames"/>
      </files>
      <linkable path="GameData\SavedGames"/>
      <contributor>GameSaveManager</contributor>
    </version>
  </game>
  <game name="ArmedForcesCorps" added="1955-11-05T00:00:00" updated="1955-11-05T00:00:00">
    <title>Armed Forces Corps</title>
    <version os="Windows">
      <locations>
        <path ev="public" path="Documents\City Interactive\Armed Forces Corps"/>
      </locations>
      <files>
        <include/>
      </files>
      <linkable/>
      <contributor>Arc Angel</contributor>
    </version>
  </game>
  <game name="ArmiesOfExigo" added="1955-11-05T00:00:00" updated="1955-11-05T00:00:00">
    <title>Armies of Exigo</title>
    <version os="Windows">
      <locations>
        <path ev="userdocuments" path="Armies of Exigo"/>
      </locations>
      <files>
        <include/>
      </files>
      <linkable/>
      <contributor>GameSaveManager</contributor>
    </version>
  </game>
  <game name="ArtificialAcademy" added="1955-11-05T00:00:00" updated="1955-11-05T00:00:00">
    <title>Artificial Academy</title>
    <version os="Windows">
      <locations>
        <registry root="current_user" key="SOFTWARE\ILLUSION\AAPLAY" value="INSTALLDIR"/>
        <registry root="local_machine" key="SOFTWARE\ILLUSION\AAPLAY" value="INSTALLDIR"/>
      </locations>
      <files>
        <include path="data\save"/>
      </files>
      <linkable path="data\save"/>
      <contributor>GameSaveManager</contributor>
    </version>
  </game>
  <game name="ArtOfMurderFBIConfidential" added="2013-01-05T16:19:39" updated="2013-01-05T16:19:39">
    <title>Art of Murder - FBI Confidential</title>
    <version os="Windows">
      <locations>
        <path ev="savedgames" path="Art of Murder FBI Confidential" only_for="WindowsVista"/>
      </locations>
      <files>
        <include/>
      </files>
      <linkable/>
      <contributor>AdmiringWorm</contributor>
    </version>
  </game>
  <game name="ArxFatalis" added="1955-11-05T00:00:00" updated="1955-11-05T00:00:00">
    <title>Arx Fatalis</title>
    <version os="Windows">
      <locations>
        <path ev="installlocation" path="GOG.com\Arx Fatalis"/>
        <registry root="local_machine" key="SOFTWARE\Arkane Studios\Installed Apps\arx fatalis" value="Folder"/>
        <registry root="local_machine" key="SOFTWARE\GOG.com\GOGARXFATALIS" value="PATH"/>
        <shortcut ev="startmenu" path="Programs\GOG.com\Arx Fatalis\Arx Fatalis.lnk"/>
      </locations>
      <files>
        <include path="Save"/>
      </files>
      <linkable path="Save"/>
      <contributor>GameSave.Info</contributor>
    </version>
  </game>
  <game name="ArxLibertatis" added="2012-10-01T16:54:44" updated="2012-10-01T16:54:44">
    <title>Arx Libertatis</title>
    <version os="Windows">
      <locations>
        <path ev="savedgames" path="Arx Libertatis"/>
      </locations>
      <files>
        <include/>
      </files>
      <linkable/>
      <contributor>GameSaveManager</contributor>
    </version>
  </game>
  <game name="AssassinsCreed" added="1955-11-05T00:00:00" updated="1955-11-05T00:00:00">
    <title>Assassin's Creed</title>
    <version os="PS3" region="USA">
      <ps_code prefix="BLUS" suffix="30089"/>
      <contributor>GameSave.Info</contributor>
    </version>
    <version os="Windows">
      <locations>
        <path ev="appdata" path="Ubisoft\Assassin's Creed"/>
      </locations>
      <files>
        <include path="Saved Games"/>
      </files>
      <files type="Settings">
        <include filename="*.ini"/>
      </files>
      <linkable/>
      <contributor>Joe Looney</contributor>
    </version>
  </game>
  <game name="AssassinsCreed2" follows="AssassinsCreedBrotherhood" added="1955-11-05T00:00:00" updated="1955-11-05T00:00:00">
    <title>Assassin's Creed 2</title>
    <version platform="UbisoftSaveStorage">
      <locations>
        <path ev="ubisoftsavestorage" path="4"/>
      </locations>
      <files>
        <include/>
      </files>
      <contributor>GameSave.Info</contributor>
    </version>
    <version os="Windows">
      <locations>
        <path ev="appdata" path="Ubisoft\Assassin's Creed 2"/>
      </locations>
      <files>
        <include/>
      </files>
      <contributor>GameSaveManager</contributor>
    </version>
  </game>
  <game name="AssassinsCreed3" added="2013-02-03T05:40:17" updated="2013-02-03T05:40:17">
    <title>Assassin's Creed 3</title>
    <version platform="UbisoftSaveStorage">
      <locations>
        <path ev="commonapplicationdata" path="Orbit\103"/>
        <path ev="ubisoftsavestorage" path="103"/>
        <path ev="ubisoftsavestorage" path="54"/>
      </locations>
      <files>
        <include/>
      </files>
      <contributor>GameSaveManager</contributor>
    </version>
    <version os="Windows">
      <locations>
        <path ev="commonapplicationdata" path="Orbit\103"/>
        <path ev="userdocuments" path="Assassin's Creed III"/>
      </locations>
      <files>
        <include/>
      </files>
      <linkable/>
      <contributor>GameSaveManager</contributor>
    </version>
  </game>
  <game name="AssassinsCreedBrotherhood" follows="AssassinsCreed" added="1955-11-05T00:00:00" updated="1955-11-05T00:00:00">
    <title>Assassin's Creed: Brotherhood</title>
    <version os="PS3" region="EU">
      <ps_code prefix="BLES" suffix="00909"/>
      <contributor>AdmiringWorm</contributor>
    </version>
    <version os="Windows">
      <locations>
        <path ev="appdata" path="Ubisoft\Assassin's Creed Brotherhood" only_for="WindowsXP"/>
        <path ev="savedgames" path="Assassin's Creed Brotherhood" only_for="WindowsVista"/>
      </locations>
      <files>
        <include/>
      </files>
      <linkable/>
      <contributor>Arc Angel</contributor>
    </version>
  </game>
  <game name="AssassinsCreedRevelations" follows="AssassinsCreed2" added="1955-11-05T00:00:00" updated="1955-11-05T00:00:00">
    <title>Assassin's Creed: Revelations</title>
    <version platform="UbisoftSaveStorage">
      <locations>
        <path ev="ubisoftsavestorage" path="40"/>
      </locations>
      <files>
        <include/>
      </files>
      <contributor>GameSave.Info</contributor>
    </version>
    <version os="PS3" region="EU">
      <ps_code prefix="BLES" suffix="01384"/>
      <contributor>AdmiringWorm</contributor>
    </version>
    <version os="Windows">
      <locations>
        <path ev="userdocuments" path="Assassin's Creed Revelations"/>
      </locations>
      <files>
        <include/>
      </files>
      <linkable/>
      <contributor>GameSaveManager</contributor>
    </version>
  </game>
  <game name="AsterixAtTheOlympicGames" added="1955-11-05T00:00:00" updated="1955-11-05T00:00:00">
    <title>Asterix at the Olympic Games</title>
    <version os="Windows">
      <locations>
        <path ev="userdocuments" path="Atari\Asterix at the Olympic Games"/>
      </locations>
      <files>
        <include/>
      </files>
      <linkable/>
      <contributor>GameSaveManager</contributor>
    </version>
  </game>
  <game name="AstroPop" added="1955-11-05T00:00:00" updated="1955-11-05T00:00:00">
    <title>AstroPop</title>
    <version os="Windows">
      <locations>
        <path ev="commonapplicationdata" path="PopCap Games\AstroPop"/>
      </locations>
      <files>
        <include path="users"/>
      </files>
      <linkable path="users"/>
      <contributor>GameSaveManager</contributor>
    </version>
  </game>
  <game name="AstroPopDeluxe" added="2013-06-14T05:17:42" updated="2013-06-14T05:17:42">
    <title>AstroPop Deluxe</title>
    <version os="Windows">
      <locations>
        <path ev="steamcommon" path="AstroPop Deluxe"/>
      </locations>
      <files>
        <include path="users"/>
      </files>
      <linkable path="users"/>
      <contributor>GameSaveManager</contributor>
    </version>
  </game>
  <game name="Atlantis2BeyondAtlantis" added="2013-01-05T16:19:39" updated="2013-01-05T16:19:39">
    <title>Atlantis II: Beyond Atlantis</title>
    <version os="Windows">
      <locations>
        <path ev="installlocation" path="GOG.com\Beyond Atlantis"/>
        <registry root="local_machine" key="SOFTWARE\GOG.com\GOGATLANTIS2" value="PATH"/>
        <shortcut ev="startmenu" path="Programs\GOG.com\Beyond Atlantis\Beyond Atlantis.lnk"/>
      </locations>
      <files>
        <include path="save"/>
      </files>
      <contributor>GameSave.Info</contributor>
    </version>
  </game>
  <game name="Atlantis3TheNewWorld" added="2013-01-05T16:19:39" updated="2013-01-05T16:19:39">
    <title>Atlantis III: The New World</title>
    <version os="Windows">
      <locations>
        <path ev="installlocation" path="GOG.com\Atlantis III - The New World"/>
        <registry root="local_machine" key="SOFTWARE\GOG.com\GOGATLANTIS3" value="PATH"/>
        <shortcut ev="startmenu" path="Programs\GOG.com\Atlantis III - The New World\Atlantis III - The New World.ln"/>
      </locations>
      <files>
        <include path="Datas\save"/>
      </files>
      <contributor>GameSave.Info</contributor>
    </version>
  </game>
  <game name="AtlantisTheLostTales" added="2013-01-05T16:19:39" updated="2013-01-05T16:19:39">
    <title>Atlantis: The Lost Tales</title>
    <version os="Windows">
      <locations>
        <path ev="installlocation" path="GOG.com\Atlantis - The Lost Tales"/>
        <registry root="current_user" key="Software\CRYO\Atlantis\GameDirectory"/>
        <registry root="local_machine" key="SOFTWARE\GOG.com\GOGATLANTIS" value="PATH"/>
        <shortcut ev="startmenu" path="Programs\GOG.com\Atlantis - The Lost Tales\Atlantis - The Lost Tales.lnk"/>
      </locations>
      <files>
        <include filename="players.atl"/>
      </files>
      <contributor>GameSave.Info</contributor>
    </version>
  </game>
  <game name="AtomicCityAdventuresTheCaseOfTheBlackDragon" added="2013-02-03T05:40:17" updated="2013-02-03T05:40:17">
    <title>Atomic City Adventures: The Case of the Black Dragon</title>
    <version os="Windows">
      <locations>
        <path ev="savedgames" path="Atomic City"/>
      </locations>
      <files>
        <include/>
      </files>
      <linkable/>
      <contributor>GameSaveManager</contributor>
    </version>
  </game>
  <game name="AtomZombieSmasher" added="1955-11-05T00:00:00" updated="1955-11-05T00:00:00">
    <title>Atom Zombie Smasher</title>
    <version os="Windows">
      <locations>
        <path ev="appdata" path="AtomZombieData"/>
      </locations>
      <files>
        <include path="profiles"/>
      </files>
      <linkable/>
      <contributor>Arc Angel</contributor>
    </version>
  </game>
  <game name="Audiosurf" added="1955-11-05T00:00:00" updated="1955-11-05T00:00:00">
    <title>Audiosurf</title>
    <version os="Windows">
      <locations>
        <path ev="steamcommon" path="audiosurf"/>
      </locations>
      <files type="Scores">
        <include path="engine\Scores"/>
      </files>
      <contributor>raize221</contributor>
    </version>
  </game>
  <game name="Auditorium" added="2013-06-14T05:17:42" updated="2013-06-14T05:17:42">
    <title>Auditorium</title>
    <version os="Windows">
      <locations>
        <path ev="appdata" path="com.cipherprime.auditorium\Local Store\#SharedObjects"/>
      </locations>
      <files>
        <include>
          <exclude filename="lastLevel.sol"/>
        </include>
      </files>
      <linkable/>
      <contributor>GameSaveManager</contributor>
    </version>
  </game>
  <game name="AutoClubRevolution" added="2013-02-03T05:40:17" updated="2013-02-03T05:40:17">
    <title>AutoClubRevolution</title>
    <version os="Windows">
      <locations>
        <registry root="local_machine" key="SOFTWARE\Eutechnyx\Auto Club Revolution Online\AutoClubRev\Preferences" value="InstallPath"/>
      </locations>
      <files>
        <include path="AutoClubRev\bin" filename="Config.ini"/>
      </files>
      <contributor>GameSaveManager</contributor>
    </version>
  </game>
  <game name="AutumnsTreasuresTheJadeCoin" added="2013-02-03T05:40:17" updated="2013-02-03T05:40:17">
    <title>Autumn's Treasures: The Jade Coin</title>
    <version os="Windows">
      <locations>
        <path ev="appdata" path="PoBros\Autumns Treasures"/>
      </locations>
      <files>
        <include/>
      </files>
      <linkable/>
      <contributor>GameSaveManager</contributor>
    </version>
  </game>
  <game name="AvadonTheBlackFortress" added="1955-11-05T00:00:00" updated="1955-11-05T00:00:00">
    <title>Avadon: The Black Fortress</title>
    <version os="Windows">
      <locations>
        <path ev="userdocuments" path="Spiderweb Software\Avadon Saved Games"/>
      </locations>
      <files>
        <include/>
      </files>
      <linkable/>
      <contributor>Arc Angel</contributor>
    </version>
  </game>
  <game name="AValleyWithoutWind" added="2012-10-01T16:54:44" updated="2012-10-01T16:54:44">
    <title>A Valley Without Wind</title>
    <version os="Windows">
      <locations>
        <path ev="steamcommon" path="a valley without wind"/>
      </locations>
      <files>
        <include path="RuntimeData\WorldBackups"/>
        <include path="RuntimeData\Worlds"/>
      </files>
      <contributor>GameSaveManager</contributor>
    </version>
  </game>
  <game name="AvatarTheGame" added="1955-11-05T00:00:00" updated="1955-11-05T00:00:00">
    <title>James Cameron's Avatar: The Game</title>
    <version os="Windows">
      <locations>
        <path ev="userdocuments" path="My Games\Avatar"/>
      </locations>
      <files>
        <include/>
      </files>
      <linkable/>
      <contributor>Arc Angel</contributor>
    </version>
  </game>
  <game name="AvencastRiseOfTheMage" added="1955-11-05T00:00:00" updated="1955-11-05T00:00:00">
    <title>Avencast: Rise of the Mage</title>
    <version os="Windows">
      <locations>
        <path ev="installlocation" path="Avencast"/>
        <path ev="steamcommon" path="avencasts"/>
        <registry root="local_machine" key="SOFTWARE\ClockStone\Avencast" value="InstallPath"/>
        <shortcut ev="startmenu" path="Programs\Avencast\Avencast.lnk"/>
      </locations>
      <files>
        <include path="save"/>
      </files>
      <linkable path="save"/>
      <contributor>Arc Angel</contributor>
      <contributor>GameSaveManager</contributor>
    </version>
  </game>
  <game name="AvenueFlo" added="1955-11-05T00:00:00" updated="1955-11-05T00:00:00">
    <title>Avenue Flo</title>
    <version os="Windows">
      <locations>
        <path ev="appdata" path="PlayFirst\avenue-flo"/>
      </locations>
      <files>
        <include/>
      </files>
      <linkable/>
      <contributor>GameSaveManager</contributor>
    </version>
  </game>
  <game name="AvernumEscapeFromthePit" added="2012-08-07T19:25:20" updated="2012-08-07T19:25:20">
    <title>Avernum Escape From the Pit</title>
    <version os="Windows">
      <locations>
        <path ev="userdocuments" path="Spiderweb Software\Avernum Saved Games"/>
      </locations>
      <files>
        <include/>
      </files>
      <linkable/>
      <contributor>Arc Angel</contributor>
    </version>
  </game>
  <game name="Aveyond1RhensQuest" added="1955-11-05T00:00:00" updated="1955-11-05T00:00:00">
    <title>Aveyond I: Rhen's Quest</title>
    <version os="Windows">
      <locations>
        <path ev="appdata" path="Aveyond I"/>
      </locations>
      <files>
        <include/>
      </files>
      <linkable/>
      <contributor>GameSaveManager</contributor>
    </version>
  </game>
  <game name="Aveyond2EansQuest" added="1955-11-05T00:00:00" updated="1955-11-05T00:00:00">
    <title>Aveyond II: Ean's Quest</title>
    <version os="Windows">
      <locations>
        <path ev="appdata" path="Aveyond II"/>
      </locations>
      <files>
        <include/>
      </files>
      <linkable/>
      <contributor>GameSaveManager</contributor>
    </version>
  </game>
  <game name="AVirusNamedTom" added="2013-02-03T05:40:17" updated="2013-02-03T05:40:17">
    <title>A Virus Named Tom</title>
    <version os="Windows">
      <locations>
        <path ev="userdocuments" path="SavedGames\AVNT"/>
      </locations>
      <files>
        <include/>
      </files>
      <linkable/>
      <contributor>GameSaveManager</contributor>
    </version>
  </game>
  <game name="AwakeningTheDreamlessCastle" added="2013-02-03T05:40:17" updated="2013-02-03T05:40:17">
    <title>Awakening: The Dreamless Castle</title>
    <version os="Windows">
      <locations>
        <path ev="appdata" path="Boomzap\awakening_dreamless_castle"/>
      </locations>
      <files>
        <include/>
      </files>
      <linkable/>
      <contributor>GameSaveManager</contributor>
    </version>
  </game>
  <game name="AWalkInTheDark" added="2013-02-23T21:39:00" updated="2013-02-23T21:39:00">
    <title>A Walk In The Dark</title>
    <version os="Windows">
      <locations>
        <path ev="userdocuments" path="SavedGames\AWalkInTheDark"/>
      </locations>
      <files>
        <include/>
      </files>
      <linkable/>
      <contributor>GameSaveManager</contributor>
    </version>
  </game>
  <game name="Awesomenauts" added="2013-02-03T05:40:17" updated="2013-02-03T05:40:17">
    <title>Awesomenauts</title>
    <version platform="SteamCloud">
      <locations>
        <path ev="steamuserdata" path="204300"/>
      </locations>
      <files>
        <include/>
      </files>
      <contributor>GameSaveManager</contributor>
    </version>
  </game>
  <game name="AxisAllies" added="2013-02-03T05:40:17" updated="2013-02-03T05:40:17">
    <title>Axis &amp; Allies</title>
    <version os="Windows" release="2004">
      <title>Axis &amp; Allies (2004)</title>
      <locations>
        <path ev="userdocuments" path="A&amp;A"/>
      </locations>
      <files>
        <include/>
      </files>
      <linkable/>
      <contributor>GameSaveManager</contributor>
    </version>
  </game>
  <game name="AxisAndAllies" added="1955-11-05T00:00:00" updated="1955-11-05T00:00:00">
    <title>Axis &amp; Allies</title>
    <version os="Windows">
      <locations>
        <path ev="installlocation" path="Hasbro Interactive\Axis and Allies"/>
        <registry root="local_machine" key="SOFTWARE\Hasbro Interactive\Axis and Allies" value="InstallPath"/>
        <shortcut ev="startmenu" path="Programs\Axis &amp; Allies\Axis &amp; Allies.lnk"/>
      </locations>
      <files>
        <include path="SaveGames"/>
      </files>
      <linkable path="SaveGames"/>
      <contributor>David Barbour</contributor>
    </version>
  </game>
  <game name="Azada" added="1955-11-05T00:00:00" updated="1955-11-05T00:00:00">
    <title>Azada</title>
    <version os="Windows">
      <locations>
        <path ev="appdata" path="Big Fish Games\Azada"/>
      </locations>
      <files>
        <include/>
      </files>
      <linkable/>
      <contributor>GameSaveManager</contributor>
    </version>
  </game>
  <game name="AzadaAncientMagic" added="2013-02-03T05:40:17" updated="2013-02-03T05:40:17">
    <title>Azada: Ancient Magic</title>
    <version os="Windows">
      <locations>
        <path ev="appdata" path="Big Fish Games\Azada Ancient Magic"/>
      </locations>
      <files>
        <include/>
      </files>
      <linkable/>
      <contributor>GameSaveManager</contributor>
    </version>
  </game>
  <game name="Aztaka" added="1955-11-05T00:00:00" updated="1955-11-05T00:00:00">
    <title>Aztaka</title>
    <version os="Windows">
      <locations>
        <path ev="localappdata" path="Aztaka"/>
        <path ev="steamcommon" path="aztaka"/>
      </locations>
      <files type="Profiles">
        <include path="Profiles"/>
      </files>
      <linkable path="Profiles"/>
      <contributor>GameSaveManager</contributor>
      <contributor>telroa</contributor>
    </version>
  </game>
</programs>
